pydacefit/__init__.py
pydacefit/boxmin.py
pydacefit/corr.py
pydacefit/dace.py
pydacefit/fit.py
pydacefit/regr.py
pydacefit/usage.py
pydacefit-1.0.1.dist-info/METADATA
pydacefit-1.0.1.dist-info/RECORD
pydacefit-1.0.1.dist-info/WHEEL
pydacefit-1.0.1.dist-info/top_level.txt
