Metadata-Version: 2.1
Name: pydacefit
Version: 1.0.1
Summary: Surrogate Model
Home-page: https://github.com/msu-coinlab/pydacefit
Author: Julian Blank
Author-email: blankjul@egr.msu.edu
License: Apache License 2.0
Keywords: metamodel,surrogate,response surface
Platform: any
Requires-Dist: numpy (>=1.15)
